{
  "_id": "62ab384ae3fa5c001926a2fd",
  "ED_Division": "GA",
  "ED_DecisionNumber": "76/562",
  "ED_Type": "Other Decisions",
  "ED_Title": "International meeting entitled \u201cStockholm+50: a healthy planet for the prosperity of all \u2013 our responsibility, our opportunity\u201d",
  "ED_Meeting": [
    {
      "_id": "62ab384ae3fa5c001926a2fe",
      "ED_Date": "2022-05-10T04:00:00.000Z",
      "ED_Number": "71st plenary meeting"
    }
  ],
  "ED_AgendaItem": "20",
  "ED_Plenary_Committee": "Plenary",
  "ED_Session": "76th session of the General Assembly",
  "ED_OriginatingBody": "Plenary",
  "ED_DecisionText": "At its 71st plenary meeting, on 10 May 2022, the General Assembly, on the proposal of its President, (footnote: A/76/L.53), recalling its resolutions 75/280 of 24 May 2021 and 75/326 of 10 September 2021 pertaining to the international meeting entitled \u201cStockholm+50: a healthy planet for the prosperity of all \u2013 our responsibility, our opportunity\u201d, to be held in Stockholm on 2 and 3 June 2022, decided, without setting a precedent for future international meetings, that States and the European Union  (footnote: In the case of the European Union, the pre-recorded statement shall be made by the President of the European Council or the President of the European Commission.) speaking at the plenary meetings might each submit a pre-recorded statement of their Head of State or Government, which would be played during the general debate of the international meeting, following its introduction by the presiding officer.\n",
  "ED_Disclaimer": "The final text of this decision will be contained in document A/76/49 (Vol. III) after editorial review.",
  "ED_MarkNew": false,
  "ED_MarkUpdated": false,
  "DEC_NotificationSent": true,
  "__v": 0,
  "DEC_NotificationSentTime": "2022-06-17T00:00:00.114Z"
}