{
  "symbol": "A/RES/73/89",
  "filename": "A_RES_73_89.pdf",
  "title": "73/89. Comprehensive, just and lasting peace in the Middle East",
  "text": "United Nations \nA/RES/73/89\n \n \nGeneral Assembly \nDistr.: General \n18 December 2018 \n \n18-21198 (E)    201218 \n*1821198* \n \n \nSeventy-third session \nAgenda item 38 \n \n \n \n \n Resolution adopted by the General Assembly \non 6 December 2018 \n \n \n \n \n[without reference to a Main Committee (A/73/L.49)] \n \n \n \n73/89. Comprehensive, just and lasting peace in the Middle East \n \n \n \nThe General Assembly, \n \nRecalling its relevant resolutions, \n \nGuided by the purposes and principles of the Charter of the United Nations, \n \nReiterates its call for the achievement, without delay, of a comprehensive, just \nand lasting peace in the Middle East on the basis of the relevant United Nations \nresolutions, including Security Council resolution 2334 (2016) of 23 December 2016, \nthe Madrid terms of reference, including the principle of land for peace, the Arab \nPeace Initiative1 and the Quartet road map,2 and an end to the Israeli occupation that \nbegan in 1967, including of East Jerusalem, and reaffirms in this regard its \nunwavering support, in accordance with international law, for the two-State solution \nof Israel and Palestine, living side by side in peace and security within recognized \nborders, based on the pre-1967 borders. \n \n47th plenary meeting  \n6 December 2018 \n \n__________________ \n \n1  A/56/1026-S/2002/932, annex II, resolution 14/221. \n \n2  S/2003/529, annex. \n",
  "paragraphs": {},
  "agenda_items": [
    "Item 38"
  ],
  "symbol_references": [
    "A/73/L.49"
  ]
}